{
  "UCWgWYZjNo42YLvx6Arb6mcg": [
    "UcnPIZaqcek",
    "jti6p8FOMI4",
    "IGdBN7VM3cs",
    "Pw_agd6SOec"
  ],
  "UC1ZHl6yHVQh579wq89_PoEA": [
    "YrV1uVvCEa4",
    "OlDIsRWg8Pc",
    "Vz2u2f-bj6c",
    "it_Y5bNDCXc",
    "NZKVdolZ5Pw",
    "pq8NxwynWGw",
    "GSslxdUSXQk",
    "3aEKIRY9uoY",
    "5Chqd6TKQw0",
    "9gZb-v90g4k",
    "A7ekBQF04oo",
    "eQL_4xErsko",
    "kphYErJWYp8",
    "p5PWbdh66i8",
    "KIvwgUBo0oc",
    "n8Fvy7dr9vU",
    "RBOoPpDgKME",
    "LWOhpgF9vrA",
    "1bTZdcx5ej0",
    "EUYO3ls__fU",
    "LjbBwmP4vto",
    "9rOqaIV7LeI",
    "nAkjQGkwdrI",
    "Tnm2Y-nPb50"
  ],
  "UCbI_tAz8drA95Qua5lMHiSg": [
    "-mNotY-Qksc",
    "wxgGkpWmRzA",
    "1usoEV7Q_CU",
    "Cezp7fiUzb4",
    "pW85EftKq3g",
    "wMtvww6r5pk",
    "tUYyRWAyg90",
    "3ZItLfx3L0w",
    "Qie8xjUaaeI",
    "9w3YfORzEe8",
    "fpKOc0aD8QM",
    "pfYkewEzW-4",
    "rZs8zkIwdyg",
    "xTWFhIZNZqs",
    "gy4N1Ksw0b4",
    "cM87Bhlv7LI",
    "pzxSJpFstzs",
    "8BVHnZgB4Ic",
    "pWlmD_6WSxo",
    "5Yd1UNs_Y0c",
    "L1QuWGHZU-g",
    "7HyN2-xMI3Y"
  ],
  "UC2I5em6UyBpQiO-8ZW0nV3w": [
    "gWZX5H7m2n8",
    "96QRPDKt5nE",
    "ZCK4v40nh90",
    "Mt_3oD6woYc",
    "oLzGkjkUDZk",
    "5bIm8JUi6Fo",
    "9Pit2Ug71DE",
    "RX8i2QH0zoA",
    "bNdrynOeqWc",
    "FPb-QIBLPS8",
    "oHPfi8e7X1c",
    "_5D0Wi2pW6g",
    "-e6yIkKZkko",
    "70nDFkAN4-k",
    "9a8HyF68_NE",
    "dSDXKml03pE",
    "q-F7t5CWnJU"
  ],
  "UCFhJ8ZFg9W4kLwFTBBNIjOw": [
    "bOQ_yDRlwmI",
    "yVZmUz_IVro",
    "SfXoX__LEM4",
    "SqdeO0Q-8TQ",
    "s7Kr5dHPcPA",
    "Uu3p60Kozig",
    "yhMPZy9df-0",
    "1myJ3EXxwCY",
    "-h06VAjTalc",
    "DOhW5uUZ6sA",
    "zRnV3MT-38o",
    "nvpp8efXBrE",
    "XcwlrMNwEAg",
    "xc8_0OOc3u4",
    "b4ZjIW6c4ME",
    "72QM3wTwFVA",
    "2VBWNKuq_cU",
    "tdxzL6Nnig8"
  ]
}